{
    "CompileStatus": "Successful",
    "stat": {
        "ru_self_cgstart": {
            "ru_maxrss_kb": 217552,
            "ru_utime_sec": 3.4399419999999998,
            "ru_stime_sec": 0.59168600000000005,
            "ru_minflt": 71408,
            "ru_majflt": 0,
            "ru_nivcsw": 15,
            "ru_nvcsw": 406
        },
        "realTime": 4.7233312129974365,
        "ru_self_end": {
            "ru_maxrss_kb": 221480,
            "ru_utime_sec": 4.3067919999999997,
            "ru_stime_sec": 0.61757700000000004,
            "ru_minflt": 72678,
            "ru_majflt": 0,
            "ru_nivcsw": 18,
            "ru_nvcsw": 408
        },
        "nQuads": 189788,
        "ru_childs_cgstart": {
            "ru_maxrss_kb": 217552,
            "ru_utime_sec": 0.15078,
            "ru_stime_sec": 0.071364999999999998,
            "ru_minflt": 17364,
            "ru_majflt": 0,
            "ru_nivcsw": 2,
            "ru_nvcsw": 54
        },
        "cpu_cycles_total": 17865693958,
        "cpu_cycles_cgstart": 867351047566954,
        "nMops": 581830,
        "mopSpeed": 669403.35512789676,
        "totalObjSize": 2140032,
        "ru_childs_end": {
            "ru_maxrss_kb": 217552,
            "ru_utime_sec": 0.15310699999999999,
            "ru_stime_sec": 0.071364999999999998,
            "ru_minflt": 17625,
            "ru_majflt": 0,
            "ru_nivcsw": 2,
            "ru_nvcsw": 55
        },
        "cpu_cycles_end": 867354444232294,
        "quadSpeed": 218353.68400222278,
        "outputSizePerQuad": 11.275907855080405,
        "mop/quad": 3.0656838156258561,
        "peak_mem_kb": 385136,
        "Frontend(%)": 80.511285121030767,
        "CodeGen(%)": 19.488714878969233
    },
    "cycles_program_begin": 867336578538336,
    "CompileProcesses": [
        "cgproc.202076.json"
    ],
    "perf": [
        {
            "stat": [
                "main",
                "entry",
                0.013029098510742188,
                0.018332999999999999,
                0.022915999999999999,
                200760,
                200760,
                0.0,
                0.0,
                1763765543.926713,
                867336578883528
            ],
            "sub": [
                {
                    "stat": [
                        "doParsingAndDesignResolution",
                        "entry",
                        0.17888522148132324,
                        0.026512000000000001,
                        0.026512000000000001,
                        209792,
                        210592,
                        0.0,
                        0.0,
                        1763765544.0925691,
                        867337207910962
                    ],
                    "sub": []
                },
                {
                    "stat": [
                        "doParsingAndDesignResolution",
                        "exit",
                        1.194735050201416,
                        0.873247,
                        0.56528999999999996,
                        361316,
                        382644,
                        0.0,
                        0.0,
                        1763765545.1084189,
                        867341061028976
                    ],
                    "sub": []
                },
                {
                    "stat": [
                        "doPostDesignResolutionToVir2Vcs",
                        "entry",
                        1.2219250202178955,
                        0.89376299999999997,
                        0.56914100000000001,
                        347300,
                        382644,
                        0.0,
                        0.0028479999999999998,
                        1763765545.1356089,
                        867341164068806
                    ],
                    "sub": [
                        {
                            "stat": [
                                "doUptoVir2VcsNoSepCleanup",
                                "entry",
                                1.7522830963134766,
                                1.4188700000000001,
                                0.57436299999999996,
                                347876,
                                382644,
                                0.127301,
                                0.058543999999999999,
                                1763765545.665967,
                                867343175708114
                            ],
                            "sub": []
                        },
                        {
                            "stat": [
                                "doUptoVir2VcsNoSepCleanup",
                                "exit",
                                3.6051051616668701,
                                3.2544629999999999,
                                0.57665699999999998,
                                373960,
                                382644,
                                0.135682,
                                0.063962000000000005,
                                1763765547.5187891,
                                867350203254378
                            ],
                            "sub": []
                        },
                        {
                            "stat": [
                                "doRadify_vir2vcsAll",
                                "entry",
                                3.6052010059356689,
                                3.2545600000000001,
                                0.57665699999999998,
                                373960,
                                382644,
                                0.135682,
                                0.063962000000000005,
                                1763765547.5188849,
                                867350203424238
                            ],
                            "sub": []
                        },
                        {
                            "stat": [
                                "doRadify_vir2vcsAll",
                                "exit",
                                3.7892701625823975,
                                3.427654,
                                0.58759700000000004,
                                385136,
                                385136,
                                0.135682,
                                0.063962000000000005,
                                1763765547.7029541,
                                867350902126552
                            ],
                            "sub": []
                        }
                    ]
                },
                {
                    "stat": [
                        "doPostDesignResolutionToVir2Vcs",
                        "exit",
                        3.7894370555877686,
                        3.4277989999999998,
                        0.58762199999999998,
                        385136,
                        385136,
                        0.135682,
                        0.063962000000000005,
                        1763765547.7031209,
                        867350902212090
                    ],
                    "sub": []
                },
                {
                    "stat": [
                        "doGAToPass2",
                        "entry",
                        3.7894570827484131,
                        3.427816,
                        0.58762499999999995,
                        385136,
                        385136,
                        0.135682,
                        0.063962000000000005,
                        1763765547.703141,
                        867350902275740
                    ],
                    "sub": [
                        {
                            "stat": [
                                "DoPass2",
                                "entry",
                                3.827686071395874,
                                3.4398740000000001,
                                0.59167400000000003,
                                380204,
                                385136,
                                0.15078,
                                0.071364999999999998,
                                1763765547.74137,
                                867351047389950
                            ],
                            "sub": []
                        },
                        {
                            "stat": [
                                "DoPass2",
                                "exit",
                                4.7164571285247803,
                                4.3067909999999996,
                                0.61072300000000002,
                                382152,
                                385136,
                                0.15310699999999999,
                                0.071364999999999998,
                                1763765548.630141,
                                867354418304514
                            ],
                            "sub": []
                        }
                    ]
                },
                {
                    "stat": [
                        "doGAToPass2",
                        "exit",
                        4.721980094909668,
                        4.3067909999999996,
                        0.61624599999999996,
                        382152,
                        385136,
                        0.15310699999999999,
                        0.071364999999999998,
                        1763765548.635664,
                        867354439274206
                    ],
                    "sub": []
                }
            ]
        },
        {
            "stat": [
                "main",
                "exit",
                4.7232692241668701,
                4.3067909999999996,
                0.61753599999999997,
                382152,
                385136,
                0.15310699999999999,
                0.071364999999999998,
                1763765548.6369531,
                867354444125590
            ],
            "sub": []
        }
    ],
    "MlibObjs": {},
    "SIMBData": {
        "out": "amcQwB.o",
        "bytes": 430498,
        "text": 0,
        "archive": "archive.91/_202076_archive_1.a"
    },
    "NameTable": {
        "uvm_pkg": [
            "uvm_pkg",
            "zr7M1",
            "module",
            5
        ],
        "_vcs_DPI_package": [
            "_vcs_DPI_package",
            "uM9F1",
            "module",
            1
        ],
        "...MASTER...": [
            "SIM",
            "amcQw",
            "module",
            11
        ],
        "uvm_custom_install_verdi_recording": [
            "uvm_custom_install_verdi_recording",
            "EbjT3",
            "module",
            8
        ],
        "vcs_paramclassrepository": [
            "vcs_paramclassrepository",
            "hEeZs",
            "module",
            2
        ],
        "_vcs_unit__2575677783": [
            "_vcs_unit__2575677783",
            "u9gUQ",
            "module",
            13
        ],
        "top_tb": [
            "top_tb",
            "W0eJz",
            "module",
            27
        ],
        "std": [
            "std",
            "reYIK",
            "module",
            4
        ],
        "fetch_env_pkg": [
            "fetch_env_pkg",
            "WMpRM",
            "module",
            23
        ],
        "_vcs_msglog": [
            "_vcs_msglog",
            "zQBzV",
            "module",
            6
        ],
        "if_id_if": [
            "if_id_if",
            "aCE6B",
            "module",
            21
        ],
        "uvm_custom_install_recording": [
            "uvm_custom_install_recording",
            "nhiwz",
            "module",
            7
        ],
        "common": [
            "common",
            "pz2HW",
            "module",
            14
        ],
        "fetch_vseq_pkg": [
            "fetch_vseq_pkg",
            "ks0hm",
            "module",
            25
        ],
        "program_memory": [
            "program_memory",
            "WRzQQ",
            "module",
            15
        ],
        "ifu": [
            "ifu",
            "aJziF",
            "module",
            16
        ],
        "if_id_agent_pkg": [
            "if_id_agent_pkg",
            "Um6Hs",
            "module",
            22
        ],
        "bpu_if": [
            "bpu_if",
            "u202L",
            "module",
            17
        ],
        "exec_if": [
            "exec_if",
            "UJ6p0",
            "module",
            19
        ],
        "fetch_test_pkg": [
            "fetch_test_pkg",
            "Yu8QE",
            "module",
            26
        ],
        "bpu_agent_pkg": [
            "bpu_agent_pkg",
            "U3Ryp",
            "module",
            18
        ],
        "exec_agent_pkg": [
            "exec_agent_pkg",
            "Vgfad",
            "module",
            20
        ],
        "seq_pkg": [
            "seq_pkg",
            "Ftgnt",
            "module",
            24
        ]
    },
    "PrevCompiledModules": {
        "program_memory": {
            "WRzQQ_d": {
                "bytes": 23184,
                "checksum": 0,
                "mod": "program_memory",
                "mode": 4,
                "archive": "archive.91/_prev_archive_1.a",
                "out": "WRzQQ_d.o"
            }
        },
        "fetch_vseq_pkg": {
            "ks0hm_d": {
                "bytes": 8626,
                "checksum": 0,
                "mod": "fetch_vseq_pkg",
                "mode": 4,
                "archive": "archive.91/_prev_archive_1.a",
                "out": "ks0hm_d.o"
            }
        },
        "_vcs_unit__2575677783": {
            "u9gUQ_d": {
                "bytes": 18000,
                "checksum": 0,
                "mod": "_vcs_unit__2575677783",
                "mode": 4,
                "archive": "archive.91/_prev_archive_1.a",
                "out": "u9gUQ_d.o"
            }
        },
        "std": {
            "reYIK_d": {
                "bytes": 44556,
                "checksum": 0,
                "mod": "std",
                "mode": 4,
                "archive": "archive.91/_prev_archive_1.a",
                "out": "reYIK_d.o"
            }
        },
        "top_tb": {
            "W0eJz_d": {
                "bytes": 23816,
                "checksum": 0,
                "mod": "top_tb",
                "mode": 4,
                "archive": "archive.91/_prev_archive_1.a",
                "out": "W0eJz_d.o"
            }
        },
        "exec_agent_pkg": {
            "Vgfad_d": {
                "bytes": 184360,
                "checksum": 0,
                "mod": "exec_agent_pkg",
                "mode": 4,
                "archive": "archive.91/_prev_archive_1.a",
                "out": "Vgfad_d.o"
            }
        },
        "uvm_pkg": {
            "zr7M1_d": {
                "bytes": 6952878,
                "checksum": 0,
                "mod": "uvm_pkg",
                "mode": 4,
                "archive": "archive.91/_prev_archive_1.a",
                "out": "zr7M1_d.o"
            }
        },
        "vcs_paramclassrepository": {
            "hEeZs_d": {
                "bytes": 8733686,
                "checksum": 0,
                "mod": "vcs_paramclassrepository",
                "mode": 4,
                "archive": "archive.91/_prev_archive_1.a",
                "out": "hEeZs_d.o"
            }
        },
        "...MASTER...": {
            "amcQw_d": {
                "bytes": 10362,
                "checksum": 0,
                "mod": "...MASTER...",
                "mode": 4,
                "out": "objs/amcQw_d.o"
            }
        },
        "uvm_custom_install_verdi_recording": {
            "EbjT3_d": {
                "bytes": 1496494,
                "checksum": 0,
                "mod": "uvm_custom_install_verdi_recording",
                "out": "EbjT3_d.o",
                "mode": 4,
                "archive": "archive.91/_202076_archive_1.a"
            }
        },
        "if_id_agent_pkg": {
            "Um6Hs_d": {
                "bytes": 223134,
                "checksum": 0,
                "mod": "if_id_agent_pkg",
                "mode": 4,
                "archive": "archive.91/_prev_archive_1.a",
                "out": "Um6Hs_d.o"
            }
        },
        "exec_if": {
            "UJ6p0_d": {
                "bytes": 35352,
                "checksum": 0,
                "mod": "exec_if",
                "mode": 4,
                "archive": "archive.91/_prev_archive_1.a",
                "out": "UJ6p0_d.o"
            }
        },
        "bpu_agent_pkg": {
            "U3Ryp_d": {
                "bytes": 159674,
                "checksum": 0,
                "mod": "bpu_agent_pkg",
                "mode": 4,
                "archive": "archive.91/_prev_archive_1.a",
                "out": "U3Ryp_d.o"
            }
        },
        "fetch_test_pkg": {
            "Yu8QE_d": {
                "bytes": 146154,
                "checksum": 0,
                "mod": "fetch_test_pkg",
                "mode": 4,
                "archive": "archive.91/_prev_archive_1.a",
                "out": "Yu8QE_d.o"
            }
        },
        "uvm_custom_install_recording": {
            "nhiwz_d": {
                "bytes": 523148,
                "checksum": 0,
                "mod": "uvm_custom_install_recording",
                "mode": 4,
                "archive": "archive.91/_prev_archive_1.a",
                "out": "nhiwz_d.o"
            }
        },
        "fetch_env_pkg": {
            "WMpRM_d": {
                "bytes": 212680,
                "checksum": 0,
                "mod": "fetch_env_pkg",
                "out": "WMpRM_d.o",
                "mode": 4,
                "archive": "archive.91/_202076_archive_1.a"
            }
        },
        "_vcs_msglog": {
            "zQBzV_d": {
                "bytes": 11114,
                "checksum": 0,
                "mod": "_vcs_msglog",
                "mode": 4,
                "archive": "archive.91/_prev_archive_1.a",
                "out": "zQBzV_d.o"
            }
        },
        "if_id_if": {
            "aCE6B_d": {
                "bytes": 30556,
                "checksum": 0,
                "mod": "if_id_if",
                "mode": 4,
                "archive": "archive.91/_prev_archive_1.a",
                "out": "aCE6B_d.o"
            }
        },
        "common": {
            "pz2HW_d": {
                "bytes": 21908,
                "checksum": 0,
                "mod": "common",
                "mode": 4,
                "archive": "archive.91/_prev_archive_1.a",
                "out": "pz2HW_d.o"
            }
        },
        "_vcs_DPI_package": {
            "uM9F1_d": {
                "bytes": 21802,
                "checksum": 0,
                "mod": "_vcs_DPI_package",
                "mode": 4,
                "archive": "archive.91/_prev_archive_1.a",
                "out": "uM9F1_d.o"
            }
        },
        "bpu_if": {
            "u202L_d": {
                "bytes": 24574,
                "checksum": 0,
                "mod": "bpu_if",
                "mode": 4,
                "archive": "archive.91/_prev_archive_1.a",
                "out": "u202L_d.o"
            }
        },
        "ifu": {
            "aJziF_d": {
                "bytes": 110072,
                "checksum": 0,
                "mod": "ifu",
                "mode": 4,
                "archive": "archive.91/_prev_archive_1.a",
                "out": "aJziF_d.o"
            }
        },
        "seq_pkg": {
            "Ftgnt_d": {
                "bytes": 10676,
                "checksum": 0,
                "mod": "seq_pkg",
                "mode": 4,
                "archive": "archive.91/_prev_archive_1.a",
                "out": "Ftgnt_d.o"
            }
        }
    },
    "CompileStrategy": "fullobj",
    "incremental": "on",
    "cpu_cycles_pass2_start": 867351047405758,
    "CurCompileUdps": {},
    "CurCompileModules": [
        "...MASTER...",
        "vcs_paramclassrepository",
        "_vcs_DPI_package",
        "_vcs_unit__2575677783",
        "std",
        "uvm_pkg",
        "_vcs_msglog",
        "uvm_custom_install_recording",
        "uvm_custom_install_verdi_recording",
        "uvm_custom_install_verdi_recording",
        "common",
        "program_memory",
        "ifu",
        "if_id_if",
        "if_id_agent_pkg",
        "bpu_if",
        "bpu_agent_pkg",
        "exec_if",
        "exec_agent_pkg",
        "fetch_env_pkg",
        "fetch_env_pkg",
        "seq_pkg",
        "fetch_vseq_pkg",
        "fetch_test_pkg",
        "top_tb"
    ],
    "LVLData": [
        "SIM"
    ],
    "PEModules": [],
    "Misc": {
        "vcs_version": "O-2018.09-SP2_Full64",
        "vcs_build_date": "Build Date = Feb 28 2019 22:34:30",
        "master_pid": 202076,
        "VCS_HOME": "/usr/software/vcs2018/vcs/O-2018.09-SP2",
        "csrc": "csrc",
        "hostname": "",
        "default_output_dir": "csrc",
        "cwd": "/home/sjp/Desktop/ICP2_verify/ICP2_verify",
        "csrc_abs": "/home/sjp/Desktop/ICP2_verify/ICP2_verify/csrc",
        "daidir": "/home/sjp/Desktop/ICP2_verify/ICP2_verify/work_lib/simv.daidir",
        "daidir_abs": "/home/sjp/Desktop/ICP2_verify/ICP2_verify/work_lib/simv.daidir",
        "archive_dir": "archive.91"
    },
    "rlimit": {
        "data": -1,
        "stack": -1
    }
}